{
  "slug": "jonwiggins-optio",
  "featuredDate": "2026-04-12",
  "fullName": "jonwiggins/optio",
  "name": "optio",
  "owner": "jonwiggins",
  "repoUrl": "https://github.com/jonwiggins/optio",
  "homepage": "https://jonwiggins.github.io/optio/",
  "description": "Workflow orchestration for AI coding agents, from task to merged PR.",
  "language": "TypeScript",
  "stars": 862,
  "forks": 87,
  "openIssues": 1,
  "createdAt": "2026-03-19T19:50:11Z",
  "updatedAt": "2026-04-12T04:05:01Z",
  "pushedAt": "2026-04-12T04:04:57Z",
  "topics": [],
  "summaryZh": "Workflow orchestration for AI coding agents, from task to merged PR. 这类项目更偏执行与编排，适合搭自动化工作流或多代理系统。",
  "whyItMatters": "最近仍在高频更新，仓库成熟度和社区基础都不错。",
  "fitFor": "适合想做自动化助手、多 Agent 编排和企业工作流的团队。",
  "tags": [
    "Agent",
    "Coding"
  ],
  "source": "github",
  "trendScore": 98,
  "qualityScore": 91,
  "relevanceScore": 62,
  "totalScore": 88
}
